{
  "dados": [
    {
      "categoria": "demograficos",
      "indicadores": [
        {
          "indicador": "populacao_residente",
          "fonte": "SIDRA",
          "formato": "csv",
          "link": "https://sidra.ibge.gov.br/geratabela/DownloadSelecaoComplexa/1420806406"
        },
        {
          "indicador": "quantidade_de_homens",
          "fonte": "SIDRA",
          "formato": "csv",
          "link": "https://sidra.ibge.gov.br/geratabela/DownloadSelecaoComplexa/-1452430117"
        },
        {
          "indicador": "quantidade_de_mulheres",
          "fonte": "SIDRA",
          "formato": "csv",
          "link": "https://sidra.ibge.gov.br/geratabela/DownloadSelecaoComplexa/-2081871684"
        },
        {
          "indicador": "quantidade_de_residentes_urbanos",
          "fonte": "SIDRA",
          "formato": "csv",
          "link": "https://sidra.ibge.gov.br/geratabela/DownloadSelecaoComplexa/651000649"
        },
        {
          "indicador": "quantidade_de_residentes_rurais",
          "fonte": "SIDRA",
          "formato": "csv",
          "link": "https://sidra.ibge.gov.br/geratabela/DownloadSelecaoComplexa/859488008"
        },
        {
          "indicador": "populacao_residente_em_favelas",
          "fonte": "SIDRA",
          "formato": "csv",
          "link": "https://sidra.ibge.gov.br/geratabela?format=br.csv&name=tabela9884.csv&terr=NC&rank=-&query=t/9884/n1/all/n6/2108603,2107506,2111201,2111300,2112506,2109908,2103000,2105401,2112209,2105302,2114007,2100055,2102325,2109452/v/allxp/p/all/c86/95251/c2/6794/c58/95253/l/v,p%2Bc86%2Bc2,t%2Bc58"
        },
        {
          "indicador": "indice_de_desenvolvimento_humano",
          "fonte": "IPEADATA",
          "formato": "csv",
          "link": "https://www.ipeadata.gov.br/ExibeSerieR.aspx?oper=exportCSVBr&serid=2096726509&DateCarto=2010&MINDATA=1991&MAXDATA=2010&TNIVID=5&TPAID=21"
        }
      ]
    },
    {
      "categoria": "geograficos",
      "indicadores": [
        {
          "indicador": "area_territorial",
          "fonte": "SIDRA",
          "formato": "csv",
          "link": "https://sidra.ibge.gov.br/geratabela/DownloadSelecaoComplexa/-1946607256"
        },
        {
          "indicador": "densidade_demografica",
          "fonte": "SIDRA",
          "formato": "csv",
          "link": "https://sidra.ibge.gov.br/geratabela/DownloadSelecaoComplexa/1382453315"
        }
      ]
    },
    {
      "categoria": "economicos",
      "indicadores": [
        {
          "indicador": "produto_interno_bruto",
          "fonte": "SIDRA",
          "formato": "csv",
          "link": "https://sidra.ibge.gov.br/geratabela/DownloadSelecaoComplexa/-1618334337"
        }
      ]
    },
    {
      "categoria": "educacao",
      "indicadores": [
        {
          "indicador": "IDEB_anos_iniciais_2023",
          "fonte": "QEDU",
          "formato": "xlsx",
          "link": "http://cdn.novo.qedu.org.br/downloads/territorios/21/ideb_territorios-21-2023-AI.xlsx"
        },
        {
          "indicador": "IDEB_anos_iniciais_2021",
          "fonte": "QEDU",
          "formato": "xlsx",
          "link": "http://cdn.novo.qedu.org.br/downloads/territorios/21/ideb_territorios-21-2021-AI.xlsx"
        },
        {
          "indicador": "IDEB_anos_iniciais_2019",
          "fonte": "QEDU",
          "formato": "xlsx",
          "link": "http://cdn.novo.qedu.org.br/downloads/territorios/21/ideb_territorios-21-2019-AI.xlsx"
        },
        {
          "indicador": "IDEB_anos_iniciais_2017",
          "fonte": "QEDU",
          "formato": "xlsx",
          "link": "http://cdn.novo.qedu.org.br/downloads/territorios/21/ideb_territorios-21-2017-AI.xlsx"
        },
        {
          "indicador": "IDEB_anos_iniciais_2015",
          "fonte": "QEDU",
          "formato": "xlsx",
          "link": "http://cdn.novo.qedu.org.br/downloads/territorios/21/ideb_territorios-21-2015-AI.xlsx"
        },
        {
          "indicador": "IDEB_anos_iniciais_2013",
          "fonte": "QEDU",
          "formato": "xlsx",
          "link": "http://cdn.novo.qedu.org.br/downloads/territorios/21/ideb_territorios-21-2013-AI.xlsx"
        },
        {
          "indicador": "IDEB_anos_iniciais_2011",
          "fonte": "QEDU",
          "formato": "xlsx",
          "link": "http://cdn.novo.qedu.org.br/downloads/territorios/21/ideb_territorios-21-2011-AI.xlsx"
        },
        {
          "indicador": "IDEB_anos_iniciais_2009",
          "fonte": "QEDU",
          "formato": "xlsx",
          "link": "http://cdn.novo.qedu.org.br/downloads/territorios/21/ideb_territorios-21-2009-AI.xlsx"
        },
        {
          "indicador": "IDEB_anos_iniciais_2007",
          "fonte": "QEDU",
          "formato": "xlsx",
          "link": "http://cdn.novo.qedu.org.br/downloads/territorios/21/ideb_territorios-21-2007-AI.xlsx"
        },
        {
          "indicador": "IDEB_anos_iniciais_2005",
          "fonte": "QEDU",
          "formato": "xlsx",
          "link": "http://cdn.novo.qedu.org.br/downloads/territorios/21/ideb_territorios-21-2005-AI.xlsx"
        },
        {
          "indicador": "IDEB_anos_finais_2023",
          "fonte": "QEDU",
          "formato": "xlsx",
          "link": "http://cdn.novo.qedu.org.br/downloads/territorios/21/ideb_territorios-21-2023-AF.xlsx"
        },
        {
          "indicador": "IDEB_anos_finais_2021",
          "fonte": "QEDU",
          "formato": "xlsx",
          "link": "http://cdn.novo.qedu.org.br/downloads/territorios/21/ideb_territorios-21-2021-AF.xlsx"
        },
        {
          "indicador": "IDEB_anos_finais_2019",
          "fonte": "QEDU",
          "formato": "xlsx",
          "link": "http://cdn.novo.qedu.org.br/downloads/territorios/21/ideb_territorios-21-2019-AF.xlsx"
        },
        {
          "indicador": "IDEB_anos_finais_2017",
          "fonte": "QEDU",
          "formato": "xlsx",
          "link": "http://cdn.novo.qedu.org.br/downloads/territorios/21/ideb_territorios-21-2019-AF.xlsx"
        },
        {
          "indicador": "IDEB_anos_finais_2015",
          "fonte": "QEDU",
          "formato": "xlsx",
          "link": "http://cdn.novo.qedu.org.br/downloads/territorios/21/ideb_territorios-21-2019-AF.xlsx"
        },
        {
          "indicador": "IDEB_ensino_medio_2023",
          "fonte": "QEDU",
          "formato": "xlsx",
          "link": "http://cdn.novo.qedu.org.br/downloads/territorios/21/ideb_territorios-21-2023-EM.xlsx"
        },
        {
          "indicador": "IDEB_ensino_medio_2021",
          "fonte": "QEDU",
          "formato": "xlsx",
          "link": "http://cdn.novo.qedu.org.br/downloads/territorios/21/ideb_territorios-21-2023-EM.xlsx"
        },
        {
          "indicador": "IDEB_ensino_medio_2019",
          "fonte": "QEDU",
          "formato": "xlsx",
          "link": "http://cdn.novo.qedu.org.br/downloads/territorios/21/ideb_territorios-21-2023-EM.xlsx"
        },
        {
          "indicador": "IDEB_ensino_medio_2017",
          "fonte": "QEDU",
          "formato": "xlsx",
          "link": "http://cdn.novo.qedu.org.br/downloads/territorios/21/ideb_territorios-21-2017-EM.xlsx"
        },
        {
          "indicador": "IDEB_ensino_medio_2015",
          "fonte": "QEDU",
          "formato": "xlsx",
          "link": "http://cdn.novo.qedu.org.br/downloads/territorios/21/ideb_territorios-21-2015-EM.xlsx"
        },
        {
          "indicador": "IDEB_ensino_medio_2013",
          "fonte": "QEDU",
          "formato": "xlsx",
          "link": "http://cdn.novo.qedu.org.br/downloads/territorios/21/ideb_territorios-21-2015-EM.xlsx"
        },
        {
          "indicador": "IDEB_ensino_medio_2011",
          "fonte": "QEDU",
          "formato": "xlsx",
          "link": "http://cdn.novo.qedu.org.br/downloads/territorios/21/ideb_territorios-21-2015-EM.xlsx"
        },
        {
          "indicador": "IDEB_ensino_medio_2009",
          "fonte": "QEDU",
          "formato": "xlsx",
          "link": "http://cdn.novo.qedu.org.br/downloads/territorios/21/ideb_territorios-21-2015-EM.xlsx"
        },
        {
          "indicador": "IDEB_ensino_medio_2007",
          "fonte": "QEDU",
          "formato": "xlsx",
          "link": "http://cdn.novo.qedu.org.br/downloads/territorios/21/ideb_territorios-21-2015-EM.xlsx"
        },
        {
          "indicador": "IDEB_ensino_medio_2005",
          "fonte": "QEDU",
          "formato": "xlsx",
          "link": "http://cdn.novo.qedu.org.br/downloads/territorios/21/ideb_territorios-21-2015-EM.xlsx"
        },
        {
          "indicador": "aprendizado_anos_iniciais_2023",
          "fonte": "QEDU",
          "formato": "xlsx",
          "link": "http://cdn.novo.qedu.org.br/downloads/territorios/21/saeb_aprendizado_territorios-21-2023-AI.xlsx"
        },
        {
          "indicador": "aprendizado_anos_iniciais_2021",
          "fonte": "QEDU",
          "formato": "xlsx",
          "link": "http://cdn.novo.qedu.org.br/downloads/territorios/21/saeb_aprendizado_territorios-21-2021-AI.xlsx"
        },
        {
          "indicador": "aprendizado_anos_iniciais_2019",
          "fonte": "QEDU",
          "formato": "xlsx",
          "link": "http://cdn.novo.qedu.org.br/downloads/territorios/21/saeb_aprendizado_territorios-21-2019-AI.xlsx"
        },
        {
          "indicador": "aprendizado_anos_iniciais_2017",
          "fonte": "QEDU",
          "formato": "xlsx",
          "link": "http://cdn.novo.qedu.org.br/downloads/territorios/21/saeb_aprendizado_territorios-21-2017-AI.xlsx"
        },
        {
          "indicador": "aprendizado_anos_iniciais_2015",
          "fonte": "QEDU",
          "formato": "xlsx",
          "link": "http://cdn.novo.qedu.org.br/downloads/territorios/21/saeb_aprendizado_territorios-21-2015-AI.xlsx"
        },
        {
          "indicador": "aprendizado_anos_finais_2023",
          "fonte": "QEDU",
          "formato": "xlsx",
          "link": "http://cdn.novo.qedu.org.br/downloads/territorios/21/saeb_aprendizado_territorios-21-2023-AF.xlsx"
        },
        {
          "indicador": "aprendizado_anos_finais_2021",
          "fonte": "QEDU",
          "formato": "xlsx",
          "link": "http://cdn.novo.qedu.org.br/downloads/territorios/21/saeb_aprendizado_territorios-21-2021-AF.xlsx"
        },
        {
          "indicador": "aprendizado_anos_finais_2019",
          "fonte": "QEDU",
          "formato": "xlsx",
          "link": "http://cdn.novo.qedu.org.br/downloads/territorios/21/saeb_aprendizado_territorios-21-2019-AF.xlsx"
        },
        {
          "indicador": "aprendizado_anos_finais_2017",
          "fonte": "QEDU",
          "formato": "xlsx",
          "link": "http://cdn.novo.qedu.org.br/downloads/territorios/21/saeb_aprendizado_territorios-21-2017-AF.xlsx"
        },
        {
          "indicador": "aprendizado_anos_finais_2015",
          "fonte": "QEDU",
          "formato": "xlsx",
          "link": "http://cdn.novo.qedu.org.br/downloads/territorios/21/saeb_aprendizado_territorios-21-2015-AF.xlsx"
        },
        {
          "indicador": "aprendizado_ensino_medio_2023",
          "fonte": "QEDU",
          "formato": "xlsx",
          "link": "http://cdn.novo.qedu.org.br/downloads/territorios/21/saeb_aprendizado_territorios-21-2023-EM.xlsx"
        },
        {
          "indicador": "aprendizado_ensino_medio_2021",
          "fonte": "QEDU",
          "formato": "xlsx",
          "link": "http://cdn.novo.qedu.org.br/downloads/territorios/21/saeb_aprendizado_territorios-21-2021-EM.xlsx"
        },
        {
          "indicador": "aprendizado_ensino_medio_2019",
          "fonte": "QEDU",
          "formato": "xlsx",
          "link": "http://cdn.novo.qedu.org.br/downloads/territorios/21/saeb_aprendizado_territorios-21-2019-EM.xlsx"
        },
        {
          "indicador": "aprendizado_ensino_medio_2017",
          "fonte": "QEDU",
          "formato": "xlsx",
          "link": "http://cdn.novo.qedu.org.br/downloads/territorios/21/saeb_aprendizado_territorios-21-2017-EM.xlsx"
        },
        {
          "indicador": "aprendizado_ensino_medio_2015",
          "fonte": "QEDU",
          "formato": "xlsx",
          "link": "http://cdn.novo.qedu.org.br/downloads/territorios/21/saeb_aprendizado_territorios-21-2015-EM.xlsx"
        },
        {
          "indicador": "percentual_de_alunos_alfabetizados",
          "fonte": "INEP",
          "formato": "xlsx",
          "link": "https://download.inep.gov.br/alfabetiza_brasil/resultados_e_metas_municipios_2024.xlsx"
        },
        {
          "indicador": "taxa_de_rendimento_anos_iniciais_2024",
          "fonte": "QEDU",
          "formato": "xlsx",
          "link": "http://cdn.novo.qedu.org.br/downloads/territorios/21/taxa_rendimento_territorios-21-2024-AI.xlsx"
        },
        {
          "indicador": "taxa_de_rendimento_anos_iniciais_2023",
          "fonte": "QEDU",
          "formato": "xlsx",
          "link": "http://cdn.novo.qedu.org.br/downloads/territorios/21/taxa_rendimento_territorios-21-2023-AI.xlsx"
        },
        {
          "indicador": "taxa_de_rendimento_anos_iniciais_2022",
          "fonte": "QEDU",
          "formato": "xlsx",
          "link": "http://cdn.novo.qedu.org.br/downloads/territorios/21/taxa_rendimento_territorios-21-2022-AI.xlsx"
        },
        {
          "indicador": "taxa_de_rendimento_anos_iniciais_2021",
          "fonte": "QEDU",
          "formato": "xlsx",
          "link": "http://cdn.novo.qedu.org.br/downloads/territorios/21/taxa_rendimento_territorios-21-2021-AI.xlsx"
        },
        {
          "indicador": "taxa_de_rendimento_anos_iniciais_2020",
          "fonte": "QEDU",
          "formato": "xlsx",
          "link": "http://cdn.novo.qedu.org.br/downloads/territorios/21/taxa_rendimento_territorios-21-2020-AI.xlsx"
        },
        {
          "indicador": "taxa_de_rendimento_anos_iniciais_2019",
          "fonte": "QEDU",
          "formato": "xlsx",
          "link": "http://cdn.novo.qedu.org.br/downloads/territorios/21/taxa_rendimento_territorios-21-2019-AI.xlsx"
        },
        {
          "indicador": "taxa_de_rendimento_anos_iniciais_2018",
          "fonte": "QEDU",
          "formato": "xlsx",
          "link": "http://cdn.novo.qedu.org.br/downloads/territorios/21/taxa_rendimento_territorios-21-2018-AI.xlsx"
        },
        {
          "indicador": "taxa_de_rendimento_anos_iniciais_2017",
          "fonte": "QEDU",
          "formato": "xlsx",
          "link": "http://cdn.novo.qedu.org.br/downloads/territorios/21/taxa_rendimento_territorios-21-2017-AI.xlsx"
        },
        {
          "indicador": "taxa_de_rendimento_anos_iniciais_2016",
          "fonte": "QEDU",
          "formato": "xlsx",
          "link": "http://cdn.novo.qedu.org.br/downloads/territorios/21/taxa_rendimento_territorios-21-2016-AI.xlsx"
        },
        {
          "indicador": "taxa_de_rendimento_anos_iniciais_2015",
          "fonte": "QEDU",
          "formato": "xlsx",
          "link": "http://cdn.novo.qedu.org.br/downloads/territorios/21/taxa_rendimento_territorios-21-2015-AI.xlsx"
        }
      ]
    },
    {
      "categoria": "saude",
      "indicadores": [
        {
          "indicador": "percentual_de_envelhecimento",
          "fonte": "SIDRA",
          "formato": "csv",
          "link": "https://sidra.ibge.gov.br/geratabela/DownloadSelecaoComplexa/1815440151"
        },
        {
          "indicador": "idade_mediana",
          "fonte": "SIDRA",
          "formato": "csv",
          "link": "https://sidra.ibge.gov.br/geratabela/DownloadSelecaoComplexa/71360697"
        },
        {
          "indicador": "pessoas_de_2_anos_ou_mais_com_deficiencia",
          "fonte": "SIDRA",
          "formato": "csv",
          "link": "https://sidra.ibge.gov.br/geratabela/DownloadSelecaoComplexa/-2107715763"
        }
      ]
    },
    {
      "categoria": "assistencia_social",
      "indicadores": [
        {
          "indicador": "indice_de_desenvolvimento_humano",
          "fonte": "IPEADATA",
          "formato": "xlsx",
          "link": "https://www.ipeadata.gov.br/ExibeSerieR.aspx?oper=exportCSVBr&serid=40037&MINDATA=2010&MAXDATA=2010&TNIVID=5&TPAID=21"
        },
        {
          "indicador": "total_de_familias_inscritas_no_cadastro_unico",
          "fonte": "SAGICAD",
          "formato": "csv",
          "link": "https://aplicacoes.cidadania.gov.br/vis/data3/v.php?q[]=oNOclsLerpibuKep3bV%2Bgmhi05Kv2rmg2a19ZW51ZXKmaX6JaV2JlmCbb2CNrMmim66Wp9icrrJyk7jNps94mb7nwJl3g5ub5ayyiXKgzM6vu7KUy%2B%2B2mJ2smlrtqMGvo027xlPQnqAgKLmdnbtVo%2BessMCgobjUU9isU6DcsZWvvKepmfznvKCQxt2jpbmv2bY%3D&ag=e&sag=21&codigo=0&ultdisp=1&ultdisp=0&ultdisp=0&wt=json&tp_funcao_consulta=0&draw=2&columns[0][data]=0&columns[0][name]=codigo&columns[0][searchable]=true&columns[0][orderable]=true&columns[0][search][value]=&columns[0][search][regex]=false&columns[1][data]=1&columns[1][name]=nome&columns[1][searchable]=true&columns[1][orderable]=true&columns[1][search][value]=&columns[1][search][regex]=false&columns[2][data]=2&columns[2][name]=sigla&columns[2][searchable]=true&columns[2][orderable]=true&columns[2][search][value]=&columns[2][search][regex]=false&columns[3][data]=3&columns[3][name]=mes_ano_formatado&columns[3][searchable]=true&columns[3][orderable]=true&columns[3][search][value]=&columns[3][search][regex]=false&columns[4][data]=4&columns[4][name]=n_fam_cad&columns[4][searchable]=true&columns[4][orderable]=true&columns[4][search][value]=&columns[4][search][regex]=false&order[0][column]=2&order[0][dir]=asc&order[1][column]=0&order[1][dir]=asc&start=0&length=3147483647&search[value]=&search[regex]=false&export=1&export_data_comma=1&export_tipo=csv&"
        },
        {
          "indicador": "familias_em_situacao_de_trabalho_infantil_cadastro_unico",
          "fonte": "SAGICAD",
          "formato": "csv",
          "link": "https://aplicacoes.cidadania.gov.br/vis/data3/v.php?q[]=oNOclsLerpibuKep3bV%2Bgmti05Kv2rmg2a19ZW51ZmymaX6JaV2JlmCbbmCNrMmim66Wp9itv6%2BZjMDPmcurp7zerph3rpam7J6ItJiZysZupaOUye6yb3e7qqecp6y%2BnKDKwKfcnpW85LuanbapmdyasYmdjsPUmKWjlMnusm93rpam7J6IiaqixN2E356h0eSxlaCtVZ7eWbOvpPAEzZzLsFPB6m13nayWre2rvG76x8XKltldmMqbwJ2wvZb9IPzwvVeRvIGn3J6Vvue1o1yxo6Dap8G3o1Co1pTYsZzB3LGZXKyaWumewMGmjsqBl9lddr7frqewuqRaPNO7t5qcd8agirCc0fCu9%2BML2KmZnbJuq5%2B4w5TWpaJ95Luanbapo%2BW1vYmzqdOc&ag=e&sag=21&codigo=0&wt=json&tp_funcao_consulta=0&draw=2&columns[0][data]=0&columns[0][name]=codigo&columns[0][searchable]=true&columns[0][orderable]=true&columns[0][search][value]=&columns[0][search][regex]=false&columns[1][data]=1&columns[1][name]=nome&columns[1][searchable]=true&columns[1][orderable]=true&columns[1][search][value]=&columns[1][search][regex]=false&columns[2][data]=2&columns[2][name]=sigla&columns[2][searchable]=true&columns[2][orderable]=true&columns[2][search][value]=&columns[2][search][regex]=false&columns[3][data]=3&columns[3][name]=mes_ano_formatado&columns[3][searchable]=true&columns[3][orderable]=true&columns[3][search][value]=&columns[3][search][regex]=false&columns[4][data]=4&columns[4][name]=n_fam_trab_infant_cad&columns[4][searchable]=true&columns[4][orderable]=true&columns[4][search][value]=&columns[4][search][regex]=false&columns[5][data]=5&columns[5][name]=n_pess_trab_infant_cad&columns[5][searchable]=true&columns[5][orderable]=true&columns[5][search][value]=&columns[5][search][regex]=false&order[0][column]=2&order[0][dir]=asc&order[1][column]=0&order[1][dir]=asc&start=0&length=3147483647&search[value]=&search[regex]=false&export=1&export_data_comma=1&export_tipo=csv&"
        },
        {
          "indicador": "familias_em_situacao_de_rua_inscritas_cadastro_unico",
          "fonte": "SAGICAD",
          "formato": "csv",
          "link": "https://aplicacoes.cidadania.gov.br/vis/data3/v.php?q[]=oNOclsLerpibuKep3bV%2Bfmhj05Kv2rmg2a19ZW51ZXKmaX6JaV2JlmCbb2CNrMmTbXuUoNqmrMGpjLrCl6WjlMnusm%2BiqaGt3nSItJiZysZupbCoyveho7CpoVrdnm20mJoaDp%2FTnqZ94LpUr7Gpr9r89BHanHfFmIqvqL6btqKvq6ej7ZrAbqWcd6SUzp6m0e28VP%2Fio6PcqMm%2BcqnT3W4%3D&ag=e&sag=21&codigo=0&wt=json&tp_funcao_consulta=0&draw=2&columns[0][data]=0&columns[0][name]=codigo&columns[0][searchable]=true&columns[0][orderable]=true&columns[0][search][value]=&columns[0][search][regex]=false&columns[1][data]=1&columns[1][name]=nome&columns[1][searchable]=true&columns[1][orderable]=true&columns[1][search][value]=&columns[1][search][regex]=false&columns[2][data]=2&columns[2][name]=sigla&columns[2][searchable]=true&columns[2][orderable]=true&columns[2][search][value]=&columns[2][search][regex]=false&columns[3][data]=3&columns[3][name]=mes_ano_formatado&columns[3][searchable]=true&columns[3][orderable]=true&columns[3][search][value]=&columns[3][search][regex]=false&columns[4][data]=4&columns[4][name]=_13_fam_sr_cad&columns[4][searchable]=true&columns[4][orderable]=true&columns[4][search][value]=&columns[4][search][regex]=false&order[0][column]=2&order[0][dir]=asc&order[1][column]=0&order[1][dir]=asc&start=0&length=3147483647&search[value]=&search[regex]=false&export=1&export_data_comma=1&export_tipo=csv&"
        },
        {
          "indicador": "programa_auxilio_gas_para_brasileiros",
          "fonte": "SAGICAD",
          "formato": "csv",
          "link": "https://aplicacoes.cidadania.gov.br/vis/data3/v.php?q[]=oNOhlMHqwJOsuqSe9WqBgrNe09Gv17llja1%2BYW16YmqqdH9%2BaWKEkmOXbWTZ8X5ldIBwoNqlwLNyk7jNps94bsPcuaehg3Ct7qZwxGhej5pu0J6f0OCImp20qJ%2B0dLOvo6C8nG7dsqCA9m5cn6mon5mwtbOlTZfXZJt1a5urbaikraNa66jCvJtVl9dkm3Vsl7W7qamtp6PcaI3EaF6PmV%2BcZlPC58CZXLaqpuVZsrybVnjebtCen9DgiJqdtKiftHSzr6OgvJxu3bKggPF%2Bb6Kpoa3edLOvo6C8nG7Qnp%2FQ4Ihvr72iXe9riLSYmcrGbtCen9DgiG%2BiqaGt3nSIwayaetxUzZ6mwpvEnKG2VXrva223qk3F0KeKq6jJ521UnbaZWrmvfn9vZZWRU96lmMubv6OxtplioXnDgHFnxdagz6%2BcwKR8dLJ5ZnKxY35%2BZ1mIilPPqabCm7upqLRVn%2Bedbstyk7jNps94mb7nwJl3g5ub5ayyiXKgzM6vsJ6gICi5nZ27VXzep7K0oJDAJNTcppTQm7GjXImqsjzmubemTZ4k1N1gib7nvKZcnKSu2qVtoJyduNSmy6GifT7tp1yulqc85rm3mKB3w5jYopnG3rb33bqem%2BxZsb1XbszZ9hepnMyblPfdu1iQ2qW8wFd6GgqX06xTweptdqG2mqA85rC3pk2Y1qst6p%2FG6m17%2F%2BmoXcmewMGmjsqBlc%2BrmMPksJ3%2F6aej2qxtsqZNmNarLeqfxupte%2F%2FpqF3LnsC%2BppvKJNTgopzQm5OVqbGho9qrssFXkcaBps%2B1on3BsqGltp6o6Fmvs6WSvcqW0wDUz%2BSup1yspFq6rsUR5JnA0FOxANTQnp2ZrquaqO2urrpXkbyBhc%2Bwo8zpwPfdvpqj7FmTr6SWw8qU3KKmfd%2B8VK%2BtramZf7K7oJvAz6LmrW7Z98lv&ag=e&sag=21&codigo=0&wt=json&tp_funcao_consulta=0&draw=2&columns[0][data]=0&columns[0][name]=codigo&columns[0][searchable]=true&columns[0][orderable]=true&columns[0][search][value]=&columns[0][search][regex]=false&columns[1][data]=1&columns[1][name]=nome&columns[1][searchable]=true&columns[1][orderable]=true&columns[1][search][value]=&columns[1][search][regex]=false&columns[2][data]=2&columns[2][name]=sigla&columns[2][searchable]=true&columns[2][orderable]=true&columns[2][search][value]=&columns[2][search][regex]=false&columns[3][data]=3&columns[3][name]=mes_ano_formatado&columns[3][searchable]=true&columns[3][orderable]=true&columns[3][search][value]=&columns[3][search][regex]=false&columns[4][data]=4&columns[4][name]=v1188&columns[4][searchable]=true&columns[4][orderable]=true&columns[4][search][value]=&columns[4][search][regex]=false&columns[5][data]=5&columns[5][name]=v1189&columns[5][searchable]=true&columns[5][orderable]=true&columns[5][search][value]=&columns[5][search][regex]=false&columns[6][data]=6&columns[6][name]=((case%20when%20t.v1188%3E0%20then%20round(t.v1189%3A%3Anumeric%2Ft.v1188%2C2)%20el&columns[6][searchable]=true&columns[6][orderable]=true&columns[6][search][value]=&columns[6][search][regex]=false&columns[7][data]=7&columns[7][name]=v1&columns[7][searchable]=true&columns[7][orderable]=true&columns[7][search][value]=&columns[7][search][regex]=false&columns[8][data]=8&columns[8][name]=v2&columns[8][searchable]=true&columns[8][orderable]=true&columns[8][search][value]=&columns[8][search][regex]=false&columns[9][data]=9&columns[9][name]=(case%20when%20t.v2%20is%20not%20null%20%20and%20t.v1188%3E0%20then%20round((t.v2%3A%3Anu&columns[9][searchable]=true&columns[9][orderable]=true&columns[9][search][value]=&columns[9][search][regex]=false&order[0][column]=2&order[0][dir]=asc&order[1][column]=0&order[1][dir]=asc&start=0&length=3147483647&search[value]=&search[regex]=false&export=1&export_data_comma=1&export_tipo=csv&"
        },
        {
          "indicador": "pessoas_inscritas_no_cadastro_unico_por_sexo",
          "fonte": "SAGICAD",
          "formato": "csv",
          "link": "https://aplicacoes.cidadania.gov.br/vis/data3/v.php?q[]=oNOclsLerpibuKep3bV%2Bymipx92g5m9jjq16ZHR1ZWu0a32AbFqIk2Cabq%2FQ4MWjm7WWrdyuubelnJLHlNawmJjhrqCvrXB135q5wZxoktSo12CmwvO8k6KtoqPnoru9cpO4zabPeJm%2B58CZd4Obm%2BWssolyoMzOr7uylMvvtpidrJpa3Z5tvpygytCU3V2XzJvAmbS3VafarLDDo5bF0FPTq6bA7baonbtVqOhZkK%2BbjsrVpdld9vfptpera4av2qfBt5uOu8ZTzqJTzeDAp6upqFrdqG3BnKXGgZnPqpzL5LujXLGjrdyrtsKYoHfPooqAlMHcwKiut1X9E6e2saapx5yv5rlu&ag=e&sag=21&codigo=0&wt=json&tp_funcao_consulta=0&draw=2&columns[0][data]=0&columns[0][name]=codigo&columns[0][searchable]=true&columns[0][orderable]=true&columns[0][search][value]=&columns[0][search][regex]=false&columns[1][data]=1&columns[1][name]=nome&columns[1][searchable]=true&columns[1][orderable]=true&columns[1][search][value]=&columns[1][search][regex]=false&columns[2][data]=2&columns[2][name]=sigla&columns[2][searchable]=true&columns[2][orderable]=true&columns[2][search][value]=&columns[2][search][regex]=false&columns[3][data]=3&columns[3][name]=mes_ano_formatado&columns[3][searchable]=true&columns[3][orderable]=true&columns[3][search][value]=&columns[3][search][regex]=false&columns[4][data]=4&columns[4][name]=sexo_masculino&columns[4][searchable]=true&columns[4][orderable]=true&columns[4][search][value]=&columns[4][search][regex]=false&columns[5][data]=5&columns[5][name]=sexo_feminino&columns[5][searchable]=true&columns[5][orderable]=true&columns[5][search][value]=&columns[5][search][regex]=false&order[0][column]=2&order[0][dir]=asc&order[1][column]=0&order[1][dir]=asc&start=0&length=3147483647&search[value]=&search[regex]=false&export=1&export_data_comma=1&export_tipo=csv&"
        },
        {
          "indicador": "pessoas_inscritas_no_cadastro_unico_por_raca_e_cor",
          "fonte": "SAGICAD",
          "formato": "csv",
          "link": "https://aplicacoes.cidadania.gov.br/vis/data3/v.php?q[]=oNOclsLerpibuKep3bWEf7Ne09Gv17lljax%2FYWyAYmqqdH9%2BaWKEkmWXbWTZ6aykobuomdurrryajrbElM54mb7nwJl3rpam7J6IiZ2Ow9SYpXim0uhwopu4mq3smL3AnKG4wJbLoW7D3LmnoYObm%2BWssolyk7jNps94btDwuleqp6Wf7Kysr6SOycafy5yWvt%2BImp20qJ%2B0n666qpKSnJnLqabCtoinsbVYqNipssGqjMfCpc6eksDcsW%2BiqaGt3nSzr6OgvJxu0J6f0OCIb6%2B9ol3nmL2zqqC2yqHOpprC6a6Tn6mZdd%2BaucGcaL3Cn92ibpjhrqCvrXB17K66caWMx8am3Zylvt6uk6%2BtoqzerL2tmo67nJnLqabCtrOVqLuadbSfrrqqkpKcpt%2Bqr67wrqKwsZmb3Z5tspxNx8am3ayU0Juvpp22mJvsWba8qpDJyqfLsFPL6m13nayWre2rvG76x8XKltlghNLcu6ilrJae3lmxs1edvNSm2Z6mfeu%2FmbCpqFrip8CxqZbLwqaKq6J9vq6YnbuprOhZEOillrrQVruylMvvtpidrJpa3Z5tvpygytCU3V2Uyty%2FmaipqFrip8CxqZbLwqaKq6J9vq6YnbuprOhZEOillrrQVruylMvvtpidrJpa3Z5tvpygytCU3V2jvu2xla9onqjsnL%2B3q47KgaHZXXa%2B366nsLqkWjzTu7eanHqyqMurp8bfrpihaJmfmamywaqcuNRT06uXICi0maqpqFrip8CxqZbLwqaKq6J9vq6YnbuprOhZEOillrrQVruylMvvtpidrJpa3Z5tvpygytCU3V2mwuhtnaqupKzmmhD1%2BtDGgabZn6XCm7%2BV%2F%2B%2BWadyov26gm8rEpdOxlNCbu6Nci5ae2qzBwKZNGvuh06Ci2euIsLjEcA%3D%3D&ag=e&sag=21&codigo=0&wt=json&tp_funcao_consulta=0&draw=2&columns[0][data]=0&columns[0][name]=codigo&columns[0][searchable]=true&columns[0][orderable]=true&columns[0][search][value]=&columns[0][search][regex]=false&columns[1][data]=1&columns[1][name]=nome&columns[1][searchable]=true&columns[1][orderable]=true&columns[1][search][value]=&columns[1][search][regex]=false&columns[2][data]=2&columns[2][name]=sigla&columns[2][searchable]=true&columns[2][orderable]=true&columns[2][search][value]=&columns[2][search][regex]=false&columns[3][data]=3&columns[3][name]=mes_ano_formatado&columns[3][searchable]=true&columns[3][orderable]=true&columns[3][search][value]=&columns[3][search][regex]=false&columns[4][data]=4&columns[4][name]=n_pess_branca_cad&columns[4][searchable]=true&columns[4][orderable]=true&columns[4][search][value]=&columns[4][search][regex]=false&columns[5][data]=5&columns[5][name]=n_pess_preta_cad&columns[5][searchable]=true&columns[5][orderable]=true&columns[5][search][value]=&columns[5][search][regex]=false&columns[6][data]=6&columns[6][name]=n_pess_amarela_cad&columns[6][searchable]=true&columns[6][orderable]=true&columns[6][search][value]=&columns[6][search][regex]=false&columns[7][data]=7&columns[7][name]=n_pess_parda_cad&columns[7][searchable]=true&columns[7][orderable]=true&columns[7][search][value]=&columns[7][search][regex]=false&columns[8][data]=8&columns[8][name]=n_pess_indigena_cad&columns[8][searchable]=true&columns[8][orderable]=true&columns[8][search][value]=&columns[8][search][regex]=false&columns[9][data]=9&columns[9][name]=n_pess_raca_semresp_cad&columns[9][searchable]=true&columns[9][orderable]=true&columns[9][search][value]=&columns[9][search][regex]=false&order[0][column]=2&order[0][dir]=asc&order[1][column]=0&order[1][dir]=asc&start=0&length=3147483647&search[value]=&search[regex]=false&export=1&export_data_comma=1&export_tipo=csv&"
        },
        {
          "indicador": "pessoas_com_deficiencia_cadastradas_cadastro_unico",
          "fonte": "SAGICAD",
          "formato": "csv",
          "link": "https://aplicacoes.cidadania.gov.br/vis/data3/v.php?q[]=oNOclsLerpibuKep3bWEgLNe09Gv17lljax%2FYWyAYmqqdH9%2BaWKEkmWXbWTZ6aykobuomd2es7ealrzPks2el5jhrqCvrXCg2qXAs3JovcKf3aJumO7CoV%2B2lKrerMCtm5K9ypbToqG87rKhrq2oqticrrJyk7jNps94mb7nwJl3g5ub5ayyiXKgzM6vuADtyuC%2Fo1ysmlrpnsDBpo7KgZbZqlPB4LOdn7H45Oectq9XkLjFlN2xpb7frqdctqRavJqxr6qhydBTLdehxt68V4ytqK3omsBumpzEgZbLqqPMm7GZXLGZn%2BettrSgkLgk2i3gon3fspqlq579I6ewt5hNysagiq%2BY0Ou8p7Cpsaq0tcnKcg%3D%3D&ag=e&sag=21&codigo=0&wt=json&tp_funcao_consulta=0&draw=2&columns[0][data]=0&columns[0][name]=codigo&columns[0][searchable]=true&columns[0][orderable]=true&columns[0][search][value]=&columns[0][search][regex]=false&columns[1][data]=1&columns[1][name]=nome&columns[1][searchable]=true&columns[1][orderable]=true&columns[1][search][value]=&columns[1][search][regex]=false&columns[2][data]=2&columns[2][name]=sigla&columns[2][searchable]=true&columns[2][orderable]=true&columns[2][search][value]=&columns[2][search][regex]=false&columns[3][data]=3&columns[3][name]=mes_ano_formatado&columns[3][searchable]=true&columns[3][orderable]=true&columns[3][search][value]=&columns[3][search][regex]=false&columns[4][data]=4&columns[4][name]=n_pess_deficien_cad&columns[4][searchable]=true&columns[4][orderable]=true&columns[4][search][value]=&columns[4][search][regex]=false&order[0][column]=2&order[0][dir]=asc&order[1][column]=0&order[1][dir]=asc&start=0&length=3147483647&search[value]=&search[regex]=false&export=1&export_data_comma=1&export_tipo=csv&"
        },
        {
          "indicador": "domicilios_com_agua_encanada",
          "fonte": "IPEADATA",
          "formato": "csv",
          "link": "https://www.ipeadata.gov.br/ExibeSerieR.aspx?oper=exportCSVBr&serid=2096726487&tipoCarto=R&DateCarto=2010&MINDATA=1991&MAXDATA=2010&TNIVID=5&TPAID=21"
        },
        {
          "indicador": "domicilios_com_energia_eletrica",
          "fonte": "IPEADATA",
          "formato": "csv",
          "link": "https://www.ipeadata.gov.br/ExibeSerieR.aspx?oper=exportCSVBr&serid=2096726341&tipoCarto=R&DateCarto=2010&MINDATA=1991&MAXDATA=2010&TNIVID=5&TPAID=21"
        }
      ]
    }
  ]
}